rtle/__init__.py
rtle/config.py
rtle/exceptions.py
rtle/fetcher.py
rtle/utils.py
rtle-0.1.0.dist-info/METADATA
rtle-0.1.0.dist-info/WHEEL
rtle-0.1.0.dist-info/top_level.txt
rtle-0.1.0.dist-info/RECORD
