Metadata-Version: 2.4
Name: rTLE
Version: 0.1.0
Summary: Fetch TLE data for given NORAD IDs from public sources.
Author-email: Edilson Filho <jose.silva_filho@insa-rouen.fr>
License: MIT
Project-URL: Homepage, https://github.com/EdilsonFilho/rTle.git
Requires-Python: >=3.8
Requires-Dist: requests>=2.0
